README.md
setup.py
scripts/__init__.py
scripts/tcpthcmd
tcpth.cmd.egg-info/PKG-INFO
tcpth.cmd.egg-info/SOURCES.txt
tcpth.cmd.egg-info/dependency_links.txt
tcpth.cmd.egg-info/requires.txt
tcpth.cmd.egg-info/top_level.txt
tcpth_cmd/__init__.py
tcpth_cmd/cmd.py
tcpth_cmd/color_string.py
tcpth_cmd/main.py
tcpth_cmd/printer.py